CHANGES.rst
CONTRIBUTORS.rst
DEVELOP.rst
LICENSE.rst
MANIFEST.in
README.rst
setup.cfg
setup.py
docs/conf.py
docs/index.rst
src/collective/__init__.py
src/collective.contract_management.egg-info/PKG-INFO
src/collective.contract_management.egg-info/SOURCES.txt
src/collective.contract_management.egg-info/dependency_links.txt
src/collective.contract_management.egg-info/entry_points.txt
src/collective.contract_management.egg-info/namespace_packages.txt
src/collective.contract_management.egg-info/not-zip-safe
src/collective.contract_management.egg-info/requires.txt
src/collective.contract_management.egg-info/top_level.txt
src/collective/contract_management/__init__.py
src/collective/contract_management/configure.zcml
src/collective/contract_management/ical.py
src/collective/contract_management/interfaces.py
src/collective/contract_management/permissions.zcml
src/collective/contract_management/setuphandlers.py
src/collective/contract_management/testing.py
src/collective/contract_management/browser/__init__.py
src/collective/contract_management/browser/configure.zcml
src/collective/contract_management/browser/overrides/.gitkeep
src/collective/contract_management/browser/static/.gitkeep
src/collective/contract_management/browser/static/main.less
src/collective/contract_management/browser/static/main.min.css
src/collective/contract_management/browser/static/main.min.css.map
src/collective/contract_management/content/__init__.py
src/collective/contract_management/content/contract.py
src/collective/contract_management/content/contracts.py
src/collective/contract_management/indexers/__init__.py
src/collective/contract_management/indexers/configure.zcml
src/collective/contract_management/indexers/contract_reminder.py
src/collective/contract_management/indexers/contract_reminder.zcml
src/collective/contract_management/locales/README.rst
src/collective/contract_management/locales/__init__.py
src/collective/contract_management/locales/collective.contract_management.pot
src/collective/contract_management/locales/update.py
src/collective/contract_management/locales/update.sh
src/collective/contract_management/locales/de/LC_MESSAGES/collective.contract_management.po
src/collective/contract_management/locales/en/LC_MESSAGES/collective.contract_management.po
src/collective/contract_management/profiles/default/browserlayer.xml
src/collective/contract_management/profiles/default/catalog.xml
