Metadata-Version: 2.1
Name: collective.contract-management
Version: 2.0b5
Summary: Contract management for Plone. Kepp track of company contracts and there contract duration.
Home-page: https://github.com/collective/collective.contract_management
Author: Maik Derstappen
Author-email: md@derico.de
License: GPL version 2
Project-URL: Source, https://github.com/collective/collective.contract_management
Project-URL: Tracker, https://github.com/collective/collective.contract_management/issues
Project-URL: PyPI, https://pypi.python.org/pypi/collective.contract_management
Keywords: Python Plone
Platform: UNKNOWN
Classifier: Environment :: Web Environment
Classifier: Framework :: Plone
Classifier: Framework :: Plone :: Addon
Classifier: Framework :: Plone :: 5.1
Classifier: Framework :: Plone :: 5.2
Classifier: Programming Language :: Python
Classifier: Programming Language :: Python :: 2.7
Classifier: Programming Language :: Python :: 3.7
Classifier: Operating System :: OS Independent
Classifier: License :: OSI Approved :: GNU General Public License v2 (GPLv2)
Requires-Python: ==2.7, >=3.6
Provides-Extra: test
Provides-Extra: collectionfilter
